instagram_grabber/__init__.py
instagram_grabber/account_dat_creator.py
instagram_grabber/get_id.py
instagram_grabber/instagram_grabber.py
instagram_grabber-1.2.dist-info/METADATA
instagram_grabber-1.2.dist-info/WHEEL
instagram_grabber-1.2.dist-info/top_level.txt
instagram_grabber-1.2.dist-info/RECORD
