Metadata-Version: 2.1
Name: instagram-grabber
Version: 1.2
Summary: Tool for grabbing profile data, Instagram ID, block users and more...
Home-page: https://github.com/Aspoky/instagram_grabber/
Author: Aspoky
Author-email: 
License: MIT
Platform: UNKNOWN
Requires-Python: >=3.6.0
Requires-Dist: selenium (>=3.14.1)
Requires-Dist: fake-useragent (>=0.1.11)
